get_context/__init__.py
get_context/cli.py
get_context/directory_structure.py
get_context/file_utils.py
get_context/ignore_utils.py
get_context/merger.py
get_context-0.1.1.dist-info/LICENSE
get_context-0.1.1.dist-info/METADATA
get_context-0.1.1.dist-info/WHEEL
get_context-0.1.1.dist-info/entry_points.txt
get_context-0.1.1.dist-info/top_level.txt
get_context-0.1.1.dist-info/RECORD
