Metadata-Version: 2.1
Name: get_context
Version: 0.1.1
Summary: Generates a single text document for a directory
Home-page: https://github.com/Aiden2244/get-context
Author: Aiden R. McCormack
Author-email: aidenm2244@proton.me
Classifier: Programming Language :: Python :: 3
Classifier: License :: OSI Approved :: MIT License
Classifier: Operating System :: OS Independent
License-File: LICENSE
Requires-Dist: pathspec >=0.9.0
